colorutil/__init__.py
colorutil/colorutil.py
colorutil/colorutil.py.pclprof
colorutil-0.9.10.dist-info/WHEEL
colorutil-0.9.10.dist-info/METADATA
colorutil-0.9.10.dist-info/RECORD
